Metadata-Version: 2.1
Name: pyscrapetrain
Version: 0.1.2
Summary: CLI for downloading TrakTrain tracks
Home-page: https://github.com/tim-morriss/pyscrapeTrain
Download-URL: https://github.com/tim-morriss/pyscrapeTrain/archive/refs/tags/v0.1.2.tar.gz
Author: Tim Morriss
License: MIT
Keywords: traktrain,scrapeTrain
Classifier: Development Status :: 4 - Beta
Classifier: Intended Audience :: End Users/Desktop
Classifier: Topic :: Multimedia :: Sound/Audio
Classifier: License :: OSI Approved :: MIT License
Classifier: Programming Language :: Python :: 3.8
Classifier: Programming Language :: Python :: 3.9
Classifier: Programming Language :: Python :: 3.10
Classifier: Programming Language :: Python :: 3.11
Classifier: Programming Language :: Python :: 3.12
Classifier: Programming Language :: Python :: 3.13
Requires-Python: >=3.8
License-File: LICENSE
